U9/dataMemory/dataMemory.vhdl
LIBRARY IEEE;
USE IEEE.STD_LOGIC_1164.ALL;
use IEEE.NUMERIC_STD.ALL;
ENTITY dataMemory IS
	PORT (
		address   : IN STD_LOGIC_VECTOR (31 DOWNTO 0);
		writeData : IN STD_LOGIC_VECTOR (31 DOWNTO 0);
		memRead   : IN STD_LOGIC;
		memWrite  : IN STD_LOGIC;
		readData  : OUT STD_LOGIC_VECTOR (31 DOWNTO 0)
	);
END dataMemory;
ARCHITECTURE Behavioral OF dataMemory IS
	TYPE RAM_16_x_32 IS ARRAY(0 TO 15) OF std_logic_vector(31 DOWNTO 0);
	SIGNAL DM : RAM_16_x_32 := (
		x"00000000", -- assume starts at 0x1000100000
		x"00000000",
		x"00000000",
		x"00000000",
		x"00000000",
		x"00000000",
		x"00000000",
		x"00000000",
		x"00000000",
		x"00000000",
		x"00000000",
		x"00000000",
		x"00000000",
		x"00000000",
		x"00000000",
		x"00000000"
	);
BEGIN
	PROCESS (memWrite, memRead) -- pulse on write
	-- Note: 268500992 = 0x10010000
	BEGIN
		IF (memWrite = '1') THEN
			DM((to_integer(unsigned(address)) - 268500992) / 4) <= writeData;
		END IF;
		IF (memRead = '1') THEN
			readData <= DM((to_integer(unsigned(address)) - 268500992)/4);
		END IF;
		-- it gives, 0, 1, 2, 3, 4, ...
	END PROCESS;
END Behavioral;

U9/dataMemory/dataMemory_tb.vhdl
LIBRARY ieee;
USE ieee.std_logic_1164.ALL;
--USE ieee.numeric_std.ALL;
ENTITY datamemory_tb IS
END datamemory_tb;
ARCHITECTURE behavior OF datamemory_tb IS
	--Inputs
	SIGNAL tb_address   : std_logic_vector(31 DOWNTO 0) := (OTHERS => '0');
	SIGNAL tb_writeData : std_logic_vector(31 DOWNTO 0) := (OTHERS => '0');
	SIGNAL tb_memRead   : std_logic := '0';
	SIGNAL tb_memWrite  : std_logic := '0';
	--Outputs
	SIGNAL tb_readData : std_logic_vector(31 DOWNTO 0);
BEGIN
	-- Instantiate the Unit Under Test (UUT)
	uut : ENTITY work.dataMemory(Behavioral)
		PORT MAP(
			address   => tb_address,
			writeData => tb_writeData,
			memRead   => tb_memRead,
			memWrite  => tb_memWrite,
			readData  => tb_readData
		);
		-- Stimulus process
stim_proc : PROCESS
BEGIN
	-- write two memory locations
	tb_address   <= x"10010000";
	tb_writeData <= x"11112222";
	tb_memWrite  <= '0';
	WAIT FOR 10 ns;
	tb_memWrite <= '1';
	WAIT FOR 10 ns;
	tb_memWrite <= '0';
	WAIT FOR 10 ns;
	tb_address   <= x"10010004";
	tb_writeData <= x"33334444";
	tb_memWrite  <= '0';
	WAIT FOR 10 ns;
	tb_memWrite <= '1';
	WAIT FOR 10 ns;
	tb_memWrite <= '0';
	WAIT FOR 10 ns;
	-- read two memory locations
	tb_address <= x"10010000";
	tb_memRead <= '0';
	WAIT FOR 10 ns;
	tb_memRead <= '1';
	WAIT FOR 10 ns;
	tb_memRead <= '0';
	WAIT FOR 10 ns;
	tb_address <= x"10010004";
	tb_memRead <= '0';
	WAIT FOR 10 ns;
	tb_memRead <= '1';
	WAIT FOR 10 ns;
	tb_memRead <= '0';
	WAIT FOR 10 ns;
	ASSERT false
	REPORT "END"
		SEVERITY failure;
END PROCESS;
END;

U9/dataMemory/testbench.vcd
$date
  Mon Feb  8 19:54:51 2021
$end
$version
  GHDL v0
$end
$timescale
  1 fs
$end
$scope module standard $end
$upscope $end
$scope module std_logic_1164 $end
$upscope $end
$scope module numeric_std $end
$upscope $end
$scope module datamemory_tb $end
$var reg 32 ! tb_address[31:0] $end
$var reg 32 " tb_writedata[31:0] $end
$var reg 1 # tb_memread $end
$var reg 1 $ tb_memwrite $end
$var reg 32 % tb_readdata[31:0] $end
$scope module uut $end
$var reg 32 & address[31:0] $end
$var reg 32 ' writedata[31:0] $end
$var reg 1 ( memread $end
$var reg 1 ) memwrite $end
$var reg 32 * readdata[31:0] $end
$comment dm is not handled $end
$upscope $end
$upscope $end
$enddefinitions $end
#0
b00010000000000010000000000000000 !
b00010001000100010010001000100010 "
0#
0$
bUUUUUUUUUUUUUUUUUUUUUUUUUUUUUUUU %
b00010000000000010000000000000000 &
b00010001000100010010001000100010 '
0(
0)
bUUUUUUUUUUUUUUUUUUUUUUUUUUUUUUUU *
#10000000
1$
1)
#20000000
0$
0)
#30000000
b00010000000000010000000000000100 !
b00110011001100110100010001000100 "
b00010000000000010000000000000100 &
b00110011001100110100010001000100 '
#40000000
1$
1)
#50000000
0$
0)
#60000000
b00010000000000010000000000000000 !
b00010000000000010000000000000000 &
#70000000
1#
b00010001000100010010001000100010 %
1(
b00010001000100010010001000100010 *
#80000000
0#
0(
#90000000
b00010000000000010000000000000100 !
b00010000000000010000000000000100 &
#100000000
1#
b00110011001100110100010001000100 %
1(
b00110011001100110100010001000100 *
#110000000
0#
0(
