U9/instructionmemory/instructionMemory.vhdl
LIBRARY IEEE;
USE IEEE.STD_LOGIC_1164.ALL;
USE IEEE.NUMERIC_STD.ALL;
ENTITY instructionMemory IS
	PORT (
		readAddress : IN STD_LOGIC_VECTOR (31 DOWNTO 0);
		instruction : OUT STD_LOGIC_VECTOR (31 DOWNTO 0)
	);
END instructionMemory;
ARCHITECTURE Behavioral OF instructionMemory IS
	TYPE RAM_16_x_32 IS ARRAY(0 TO 15) OF std_logic_vector(31 DOWNTO 0);
	SIGNAL IM : RAM_16_x_32 := (
		x"01285024", -- 0x0040 0000: and 	$t2, 	$t1, 	$t0
		x"018b6825", -- 0x0040 0004: or 	$t5, 	$t4, 	$t3
		x"01285020", -- 0x0040 0008: add 	$t2, 	$t1, 	$t0
		x"01285022", -- 0x0040 0004: sub 	$t5, 	$t1, 	$t0
		x"0149402a", -- 0x0040 0010: slt 	$t0, 	$t2, 	$t1
		x"1211fffb", -- 0x0040 0014: branchequal 	$s0, 	$s1, 	$L1		(1210fffb for $s1, $s1)
		x"01285024", -- 0x0040 0018: and 	$t2, 	$t1, 	$t0
		x"018b6825", -- 0x0040 001C: or 	$t5, 	$t4, 	$t3
		x"01285020", -- 0x0040 0020: add 	$t2, 	$t1, 	$t0
		x"01285022", -- 0x0040 0004: sub 	$t5, 	$t1, 	$t0
		x"0149402a", -- 0x0040 0010: slt 	$t0, 	$t2, 	$t1
		x"08100000", -- 0x0040 002C: j 0x00400000 => 0000 1000 0001 0000 0000 0000 0000 (jump to address 0x00400000 (begining))
		x"00000000",
		x"00000000",
		x"00000000",
		x"00000000"
	);
BEGIN
	-- Note: 4194304 = 0x0040 0000
	-- reset when address is 003FFFFC else if readAddress is 0040 0000 then reset also
	instruction <= x"00000000" when readAddress = x"003FFFFC" else 
		IM(( to_integer(unsigned(readAddress)) - 4194304) /4);
END Behavioral;

U9/instructionmemory/instructionMemory_tb.vhdl
LIBRARY ieee;
USE ieee.std_logic_1164.ALL;
USE IEEE.NUMERIC_STD.ALL;
ENTITY instructionMemory_tb IS
END instructionMemory_tb;
ARCHITECTURE behavior OF instructionMemory_tb IS
	--Inputs
	SIGNAL tb_readAddress : std_logic_vector(31 DOWNTO 0) := x"003fffff";
	--Outputs
	SIGNAL tb_instruction : std_logic_vector(31 DOWNTO 0);
BEGIN
	-- Instantiate the Unit Under Test (UUT)
	U1_Test : ENTITY work.instructionMemory(Behavioral)
		PORT MAP(
			readAddress => tb_readAddress,
			instruction => tb_instruction
		);
-- Stimulus process
stim_proc : PROCESS
BEGIN
	-- read 12 commands
	FOR I IN 0 TO 11 LOOP
		tb_readAddress <= x"00400000" OR std_logic_vector(to_unsigned(I * 4, 32));
		WAIT FOR 25 ns;
	END LOOP;
	ASSERT false
	REPORT "END"
		SEVERITY failure;
END PROCESS;
END;

U9/instructionmemory/testbench.vcd
$date
  Mon Feb  8 19:03:26 2021
$end
$version
  GHDL v0
$end
$timescale
  1 fs
$end
$scope module standard $end
$upscope $end
$scope module std_logic_1164 $end
$upscope $end
$scope module numeric_std $end
$upscope $end
$scope module instructionmemory_tb $end
$var reg 32 ! tb_readaddress[31:0] $end
$var reg 32 " tb_instruction[31:0] $end
$scope module u1_test $end
$var reg 32 # readaddress[31:0] $end
$var reg 32 $ instruction[31:0] $end
$comment im is not handled $end
$upscope $end
$upscope $end
$enddefinitions $end
#0
b00000000010000000000000000000000 !
b00000001001010000101000000100100 "
b00000000010000000000000000000000 #
b00000001001010000101000000100100 $
#25000000
b00000000010000000000000000000100 !
b00000001100010110110100000100101 "
b00000000010000000000000000000100 #
b00000001100010110110100000100101 $
#50000000
b00000000010000000000000000001000 !
b00000001001010000101000000100000 "
b00000000010000000000000000001000 #
b00000001001010000101000000100000 $
#75000000
b00000000010000000000000000001100 !
b00000001001010000101000000100010 "
b00000000010000000000000000001100 #
b00000001001010000101000000100010 $
#100000000
b00000000010000000000000000010000 !
b00000001010010010100000000101010 "
b00000000010000000000000000010000 #
b00000001010010010100000000101010 $
#125000000
b00000000010000000000000000010100 !
b00010010000100011111111111111011 "
b00000000010000000000000000010100 #
b00010010000100011111111111111011 $
#150000000
b00000000010000000000000000011000 !
b00000001001010000101000000100100 "
b00000000010000000000000000011000 #
b00000001001010000101000000100100 $
#175000000
b00000000010000000000000000011100 !
b00000001100010110110100000100101 "
b00000000010000000000000000011100 #
b00000001100010110110100000100101 $
#200000000
b00000000010000000000000000100000 !
b00000001001010000101000000100000 "
b00000000010000000000000000100000 #
b00000001001010000101000000100000 $
#225000000
b00000000010000000000000000100100 !
b00000001001010000101000000100010 "
b00000000010000000000000000100100 #
b00000001001010000101000000100010 $
#250000000
b00000000010000000000000000101000 !
b00000001010010010100000000101010 "
b00000000010000000000000000101000 #
b00000001010010010100000000101010 $
#275000000
b00000000010000000000000000101100 !
b00001000000100000000000000000000 "
b00000000010000000000000000101100 #
b00001000000100000000000000000000 $
